modpoll/__init__.py
modpoll/__main__.py
modpoll/arg_parser.py
modpoll/main.py
modpoll/modbus_task.py
modpoll/mqtt_task.py
modpoll/utils.py
modpoll-1.6.0.dist-info/LICENSE
modpoll-1.6.0.dist-info/METADATA
modpoll-1.6.0.dist-info/WHEEL
modpoll-1.6.0.dist-info/entry_points.txt
modpoll-1.6.0.dist-info/RECORD
