Metadata-Version: 2.1
Name: modpoll
Version: 1.6.0
Summary: A New Command-line Tool for Modbus and MQTT
Home-page: https://github.com/gavinying/modpoll
Author: Ying Shaodong
Author-email: helloysd@gmail.com
Requires-Python: >=3.10,<4.0
Classifier: Programming Language :: Python :: 3
Classifier: Programming Language :: Python :: 3.10
Classifier: Programming Language :: Python :: 3.11
Classifier: Programming Language :: Python :: 3.12
Provides-Extra: serial
Requires-Dist: paho-mqtt (>=2.1.0,<3.0.0)
Requires-Dist: prettytable (>=3.9.0,<4.0.0)
Requires-Dist: pymodbus (>=3.9.0,<3.10.0)
Requires-Dist: pyserial (>=3.5,<4.0) ; extra == "serial"
Requires-Dist: requests (>=2.32.5,<3.0.0)
Project-URL: Documentation, https://gavinying.github.io/modpoll
Project-URL: Repository, https://github.com/gavinying/modpoll
